litspy/__init__.py
litspy/__main__.py
litspy/alternative_characters.py
litspy/anatomy_qualifiers.py
litspy/create_html.py
litspy/epmc_query.py
litspy/get_synonyms.py
litspy/input_args.py
litspy/logger.py
litspy/noisy_phrases.py
litspy-0.0.6.3.data/scripts/__main__.py
litspy-0.0.6.3.dist-info/LICENCE.txt
litspy-0.0.6.3.dist-info/METADATA
litspy-0.0.6.3.dist-info/WHEEL
litspy-0.0.6.3.dist-info/top_level.txt
litspy-0.0.6.3.dist-info/RECORD
