Metadata-Version: 2.1
Name: litspy
Version: 0.0.6.3
Summary: Searches through all titles and abstracts available in Europe PMC for co-occurrence of supplied terms (and their synonyms where available), and produces summaries of the search results.
Home-page: https://github.com/ec339/litspy/tree/master/litspy
Author: E Croot
Author-email: croote@cardiff.ac.uk
License: LICENCE.txt
Classifier: Programming Language :: Python
Classifier: License :: OSI Approved :: MIT License
Classifier: Operating System :: OS Independent
Requires-Python: >=3.6
License-File: LICENCE.txt
Requires-Dist: beautifulsoup4
Requires-Dist: requests
Requires-Dist: lxml
Requires-Dist: wordcloud
Requires-Dist: pandas
Requires-Dist: matplotlib
Requires-Dist: xlrd
Requires-Dist: openpyxl
Requires-Dist: rtgo
